redub/__init__.py
redub/__main__.py
redub/rename_images.py
redub/rename_images_ui.py
redub-0.1.0.dist-info/WHEEL
redub-0.1.0.dist-info/METADATA
redub-0.1.0.dist-info/RECORD
